langchain_db2/__init__.py
langchain_db2/db2vs.py
langchain_db2/py.typed
langchain_db2/utils.py
langchain_db2-0.1.7.dist-info/LICENSE
langchain_db2-0.1.7.dist-info/METADATA
langchain_db2-0.1.7.dist-info/WHEEL
langchain_db2-0.1.7.dist-info/RECORD
