Metadata-Version: 2.1
Name: langchain-db2
Version: 0.1.7
Summary: An integration package connecting Db2 vector store and LangChain
Home-page: https://github.com/langchain-ai/langchain-ibm
License: MIT
Author: IBM
Requires-Python: >=3.9,<4.0
Classifier: License :: OSI Approved :: MIT License
Classifier: Programming Language :: Python :: 3
Classifier: Programming Language :: Python :: 3.9
Classifier: Programming Language :: Python :: 3.10
Classifier: Programming Language :: Python :: 3.11
Classifier: Programming Language :: Python :: 3.12
Requires-Dist: ibm-db (>=3.2.6,<4.0.0)
Requires-Dist: langchain-community (>=0.3.20,<0.4.0)
Requires-Dist: langchain-core (>=0.3.15,<0.4.0)
Project-URL: Repository, https://github.com/langchain-ai/langchain-ibm
Project-URL: Source Code, https://github.com/langchain-ai/langchain-ibm/tree/main/libs/langchain-db2
